README.md
setup.py
schainc/_noise.c
schainpy/__init__.py
schainpy/admin.py
schainpy/controller.py
schainpy/schain.conf.template
schainpy.egg-info/PKG-INFO
schainpy.egg-info/SOURCES.txt
schainpy.egg-info/dependency_links.txt
schainpy.egg-info/entry_points.txt
schainpy.egg-info/requires.txt
schainpy.egg-info/top_level.txt
schainpy/cli/__init__.py
schainpy/cli/cli.py
schainpy/cli/templates.py
schainpy/gui/__init__.py
schainpy/gui/schainGUI
schainpy/model/__init__.py
schainpy/model/data/BLTRheaderIO.py
schainpy/model/data/__init__.py
schainpy/model/data/jroamisr.py
schainpy/model/data/jrodata.py
schainpy/model/data/jroheaderIO.py
schainpy/model/graphics/__init__.py
schainpy/model/graphics/jroplot_base.py
schainpy/model/graphics/jroplot_correlation.py
schainpy/model/graphics/jroplot_heispectra.py
schainpy/model/graphics/jroplot_parameters.py
schainpy/model/graphics/jroplot_spectra.py
schainpy/model/graphics/jroplot_voltage.py
schainpy/model/graphics/plotting_codes.py
schainpy/model/io/MIRAtest.py
schainpy/model/io/__init__.py
schainpy/model/io/bltrIO_param.py
schainpy/model/io/bltrIO_spectra.py
schainpy/model/io/jroIO_amisr.py
schainpy/model/io/jroIO_base.py
schainpy/model/io/jroIO_digitalRF.py
schainpy/model/io/jroIO_heispectra.py
schainpy/model/io/jroIO_hf.py
schainpy/model/io/jroIO_kamisr.py
schainpy/model/io/jroIO_madrigal.py
schainpy/model/io/jroIO_matlab.py
schainpy/model/io/jroIO_mira35c.py
schainpy/model/io/jroIO_param.py
schainpy/model/io/jroIO_simulator.py
schainpy/model/io/jroIO_spectra.py
schainpy/model/io/jroIO_usrp.py
schainpy/model/io/jroIO_usrp_api.py
schainpy/model/io/jroIO_voltage.py
schainpy/model/io/julIO_param.py
schainpy/model/io/pxIO_param.py
schainpy/model/io/utils.py
schainpy/model/proc/__init__.py
schainpy/model/proc/bltrproc_parameters.py
schainpy/model/proc/jroproc_amisr.py
schainpy/model/proc/jroproc_base.py
schainpy/model/proc/jroproc_correlation.py
schainpy/model/proc/jroproc_heispectra.py
schainpy/model/proc/jroproc_parameters.py
schainpy/model/proc/jroproc_spectra.py
schainpy/model/proc/jroproc_spectra_acf.py
schainpy/model/proc/jroproc_spectra_lags.py
schainpy/model/proc/jroproc_voltage.py
